README.rst
pytest_bugtong_tag.py
setup.py
pytest_bugtong_tag.egg-info/PKG-INFO
pytest_bugtong_tag.egg-info/SOURCES.txt
pytest_bugtong_tag.egg-info/dependency_links.txt
pytest_bugtong_tag.egg-info/entry_points.txt
pytest_bugtong_tag.egg-info/requires.txt
pytest_bugtong_tag.egg-info/top_level.txt